misc/drawing.py
misc/__init__.py
graph/graph.py
graph/__init__.py
graph/graph_retrieval.py
algorithms/__init__.py
algorithms/algorithm_input.py
algorithms/base.py
algorithms/src/__init__.py
algorithms/src/algorithm1/__init__.py
algorithms/src/algorithm1/source/mstl.pyx
algorithms/src/algorithm1/binaries/__init__.py
algorithms/src/algorithm3/__init__.py
algorithms/src/algorithm3/source/postprocess.pyx
algorithms/src/algorithm3/source/tdbscan.pyx
algorithms/src/algorithm3/binaries/__init__.py
algorithms/src/algorithm2/__init__.py
algorithms/src/algorithm2/source/mknn_bfs.pyx
algorithms/src/algorithm2/source/mknn_connect.pyx
algorithms/src/algorithm2/source/mknn.pyx
algorithms/src/algorithm2/source/mknn_lp.pyx
algorithms/src/algorithm2/binaries/__init__.py
preprocess/__init__.py
preprocess/preprocessing.py
utils/__init__.py
utils/_parameter_validation.py
transductive_clustering/_algorithm2.py
transductive_clustering/_algorithm3.py
transductive_clustering/_transductive_estimator.py
transductive_clustering/__init__.py
transductive_clustering/_algorithm1.py
transatlantic_beta-0.0.0.dist-info/RECORD
transatlantic_beta-0.0.0.dist-info/WHEEL
transatlantic_beta-0.0.0.dist-info/top_level.txt
transatlantic_beta-0.0.0.dist-info/METADATA
package/algorithms/src/algorithm1/binaries/mstl.cpython-310-darwin.so
package/algorithms/src/algorithm3/binaries/postprocess.cpython-310-darwin.so
package/algorithms/src/algorithm3/binaries/tdbscan.cpython-310-darwin.so
package/algorithms/src/algorithm2/binaries/mknn_bfs.cpython-310-darwin.so
package/algorithms/src/algorithm2/binaries/mknn.cpython-310-darwin.so
package/algorithms/src/algorithm2/binaries/mknn_connect.cpython-310-darwin.so
package/algorithms/src/algorithm2/binaries/mknn_lp.cpython-310-darwin.so
